data_governance_checkup/__init__.py
data_governance_checkup/utils.py
data_governance_checkup/compliance/__init__.py
data_governance_checkup/compliance/ccpa_validator.py
data_governance_checkup/compliance/compliance_framework_validator.py
data_governance_checkup/compliance/gdpr_validator.py
data_governance_checkup/compliance/hipaa_validator.py
data_governance_checkup/compliance/iso27001_validator.py
data_governance_checkup/lineage/__init__.py
data_governance_checkup/lineage/lineage.py
data_governance_checkup/masking/__init__.py
data_governance_checkup/masking/masking.py
data_governance_checkup/metadata/__init__.py
data_governance_checkup/metadata/metadata_manager.py
data_governance_checkup/rbac/__init__.py
data_governance_checkup/rbac/rbac.py
data_governance_checkup-0.1.2.dist-info/METADATA
data_governance_checkup-0.1.2.dist-info/WHEEL
data_governance_checkup-0.1.2.dist-info/top_level.txt
data_governance_checkup-0.1.2.dist-info/RECORD
