Metadata-Version: 2.1
Name: data-governance-checkup
Version: 0.1.2
Summary: A library to simplify and enhance data governance and compliance processes
Home-page: https://github.com/pratiklahudkar/data-governance
Author: Pratik P. Lahudkar
Author-email: pratik.lahudkar@gmail.com
Classifier: Programming Language :: Python :: 3
Classifier: License :: OSI Approved :: MIT License
Classifier: Operating System :: OS Independent
Requires-Python: >=3.7
